pytest_sugar_bugfix159.py
pytest_sugar_bugfix159-1.0.dist-info/LICENSE
pytest_sugar_bugfix159-1.0.dist-info/METADATA
pytest_sugar_bugfix159-1.0.dist-info/WHEEL
pytest_sugar_bugfix159-1.0.dist-info/entry_points.txt
pytest_sugar_bugfix159-1.0.dist-info/top_level.txt
pytest_sugar_bugfix159-1.0.dist-info/RECORD
