Metadata-Version: 2.1
Name: pytest-sugar-bugfix159
Version: 1.0
Summary: Workaround for https://github.com/Frozenball/pytest-sugar/issues/159
Home-page: https://github.com/jaraco/pytest-sugar-bugfix159
Author: Jason R. Coombs
Author-email: jaraco@jaraco.com
License: UNKNOWN
Platform: UNKNOWN
Classifier: Development Status :: 5 - Production/Stable
Classifier: Intended Audience :: Developers
Classifier: License :: OSI Approved :: MIT License
Classifier: Programming Language :: Python :: 2.7
Classifier: Programming Language :: Python :: 3
Requires-Python: >=2.7
Provides-Extra: docs
Requires-Dist: sphinx; extra == 'docs'
Requires-Dist: jaraco.packaging (>=3.2); extra == 'docs'
Requires-Dist: rst.linker (>=1.9); extra == 'docs'
Provides-Extra: testing
Requires-Dist: pytest (!=3.7.3,>=3.5); extra == 'testing'
Requires-Dist: pytest-sugar (>=0.9.1); extra == 'testing'
Requires-Dist: collective.checkdocs; extra == 'testing'
Requires-Dist: pytest-flake8; extra == 'testing'
